Need to verify:true begin method@[<com.bitdefender.security.antimalware.o: void a(java.lang.String)>, <com.bitdefender.security.antimalware.l: void a(java.lang.String)>, <com.bitdefender.security.antimalware.o: void b(java.lang.String)>, <com.bitdefender.websecurity.i: void e()>, <com.bitdefender.security.antimalware.l: void a(java.lang.String,java.lang.String,int)>, <com.bitdefender.security.antimalware.l: void a(java.util.ArrayList)>, <com.bitdefender.websecurity.i: boolean b(java.lang.String,java.lang.String)>, <com.bitdefender.security.antimalware.l: void b(java.lang.String)>] lock method@[]

<com.bitdefender.security.antimalware.o: void a(java.lang.String)>
  public final void a(String paramString)
  {
    Cursor localCursor = null;
    synchronized (this.d)
    {
      a();
      this.b.beginTransaction();
    }
    try
    {
      b("PENDING_APPS", "PACKAGENAME = '" + paramString + "'");
      localCursor = a("PENDING_APPS", null);
      if (localCursor != null)
      {
        if (localCursor.getCount() == 0)
          this.f.e(true);
        while (true)
        {
          this.b.setTransactionSuccessful();
          this.b.endTransaction();
          if (localCursor != null)
            localCursor.close();
          b();
          return;
          this.f.e(false);
        }
      }
    }
    catch (SQLException localSQLException)
    {
      while (true)
      {
        c.a(localSQLException.toString());
        this.b.endTransaction();
        continue;
        localObject2 = finally;
        throw localObject2;
        h.a("NotScannedSQL", "LOG_GEO - ERROR executeQuery in deleteNotScannedApp - MalwareListSQL");
      }
    }
    finally
    {
      this.b.endTransaction();
    }
  }

<com.bitdefender.security.antimalware.l: void a(java.lang.String)>
  public final void a(String paramString)
  {
    Cursor localCursor = null;
    synchronized (this.e)
    {
      a();
      this.b.beginTransaction();
    }
    try
    {
      b("MALWARELIST", "PACKAGENAME = '" + paramString + "' AND ISFILE = 0");
      localCursor = a("MALWARELIST", null);
      if (localCursor != null)
      {
        if (localCursor.getCount() == 0)
          this.c.b(true);
        while (true)
        {
          this.b.setTransactionSuccessful();
          this.b.endTransaction();
          if (localCursor != null)
            localCursor.close();
          b();
          f();
          return;
          this.c.b(false);
        }
      }
    }
    catch (SQLException localSQLException)
    {
      while (true)
      {
        c.a(localSQLException.toString());
        this.b.endTransaction();
        continue;
        localObject2 = finally;
        throw localObject2;
        h.a("MalwareListSQL", "LOG_GEO - ERROR executeQuery in deleteMalwarePackageIfExists - MalwareListSQL");
      }
    }
    finally
    {
      this.b.endTransaction();
    }
  }


<com.bitdefender.security.antimalware.o: void b(java.lang.String)>

  public final void b(String paramString)
  {
    // Byte code:
    //   0: aload_0
    //   1: getfield 22	com/bitdefender/security/antimalware/o:d	Ljava/lang/Object;
    //   4: astore_2
    //   5: aload_2
    //   6: monitorenter
    //   7: aconst_null
    //   8: astore_3
    //   9: new 116	android/content/ContentValues
    //   12: dup
    //   13: invokespecial 117	android/content/ContentValues:<init>	()V
    //   16: astore 4
    //   18: aload 4
    //   20: ldc 119
    //   22: aload_1
    //   23: invokevirtual 122	android/content/ContentValues:put	(Ljava/lang/String;Ljava/lang/String;)V
    //   26: new 61	java/lang/StringBuilder
    //   29: dup
    //   30: ldc 63
    //   32: invokespecial 65	java/lang/StringBuilder:<init>	(Ljava/lang/String;)V
    //   35: aload_1
    //   36: invokevirtual 69	java/lang/StringBuilder:append	(Ljava/lang/String;)Ljava/lang/StringBuilder;
    //   39: ldc 71
    //   41: invokevirtual 69	java/lang/StringBuilder:append	(Ljava/lang/String;)Ljava/lang/StringBuilder;
    //   44: invokevirtual 75	java/lang/StringBuilder:toString	()Ljava/lang/String;
    //   47: astore 6
    //   49: aload_0
    //   50: invokevirtual 48	com/bitdefender/security/antimalware/o:a	()Lcom/bitdefender/security/u;
    //   53: pop
    //   54: aload_0
    //   55: getfield 52	com/bitdefender/security/antimalware/o:b	Landroid/database/sqlite/SQLiteDatabase;
    //   58: invokevirtual 57	android/database/sqlite/SQLiteDatabase:beginTransaction	()V
    //   61: aload_0
    //   62: ldc 59
    //   64: aload 6
    //   66: invokevirtual 81	com/bitdefender/security/antimalware/o:a	(Ljava/lang/String;Ljava/lang/String;)Landroid/database/Cursor;
    //   69: astore_3
    //   70: aload_3
    //   71: ifnull +51 -> 122
    //   74: aload_3
    //   75: invokeinterface 87 1 0
    //   80: ifgt +11 -> 91
    //   83: aload_0
    //   84: ldc 59
    //   86: aload 4
    //   88: invokevirtual 125	com/bitdefender/security/antimalware/o:a	(Ljava/lang/String;Landroid/content/ContentValues;)V
    //   91: aload_0
    //   92: getfield 52	com/bitdefender/security/antimalware/o:b	Landroid/database/sqlite/SQLiteDatabase;
    //   95: invokevirtual 93	android/database/sqlite/SQLiteDatabase:setTransactionSuccessful	()V
    //   98: aload_0
    //   99: getfield 52	com/bitdefender/security/antimalware/o:b	Landroid/database/sqlite/SQLiteDatabase;
    //   102: invokevirtual 96	android/database/sqlite/SQLiteDatabase:endTransaction	()V
    //   105: aload_3
    //   106: ifnull +9 -> 115
    //   109: aload_3
    //   110: invokeinterface 99 1 0
    //   115: aload_0
    //   116: invokevirtual 101	com/bitdefender/security/antimalware/o:b	()V
    //   119: aload_2
    //   120: monitorexit
    //   121: return
    //   122: ldc 108
    //   124: ldc 127
    //   126: invokestatic 114	com/bd/android/shared/h:a	(Ljava/lang/String;Ljava/lang/String;)V
    //   129: goto -38 -> 91
    //   132: astore 9
    //   134: aload 9
    //   136: invokevirtual 102	android/database/SQLException:toString	()Ljava/lang/String;
    //   139: invokestatic 106	com/bd/android/shared/c:a	(Ljava/lang/String;)V
    //   142: aload_0
    //   143: getfield 52	com/bitdefender/security/antimalware/o:b	Landroid/database/sqlite/SQLiteDatabase;
    //   146: invokevirtual 96	android/database/sqlite/SQLiteDatabase:endTransaction	()V
    //   149: goto -44 -> 105
    //   152: astore 5
    //   154: aload_2
    //   155: monitorexit
    //   156: aload 5
    //   158: athrow
    //   159: astore 8
    //   161: aload_0
    //   162: getfield 52	com/bitdefender/security/antimalware/o:b	Landroid/database/sqlite/SQLiteDatabase;
    //   165: invokevirtual 96	android/database/sqlite/SQLiteDatabase:endTransaction	()V
    //   168: aload 8
    //   170: athrow
    //
    // Exception table:
    //   from	to	target	type
    //   61	70	132	android/database/SQLException
    //   74	91	132	android/database/SQLException
    //   91	98	132	android/database/SQLException
    //   122	129	132	android/database/SQLException
    //   9	61	152	finally
    //   98	105	152	finally
    //   109	115	152	finally
    //   115	121	152	finally
    //   142	149	152	finally
    //   161	171	152	finally
    //   61	70	159	finally
    //   74	91	159	finally
    //   91	98	159	finally
    //   122	129	159	finally
    //   134	142	159	finally
  }

<com.bitdefender.websecurity.i: void e()>

  protected final void e()
  {
    String str;
    synchronized (this.e)
    {
      str = System.currentTimeMillis() + " - TIMESTAMP > 1800000";
      a();
      this.b.beginTransaction();
    }
    try
    {
      a("WHITELIST_SDK", str);
      this.b.setTransactionSuccessful();
      this.b.endTransaction();
      b();
      return;
    }
    catch (SQLException localSQLException)
    {
      while (true)
      {
        c.a("WebSecuritySDK - WebSecuritySQL - updateTimeStamp: " + localSQLException.toString());
        this.b.endTransaction();
      }
      localObject2 = finally;
      throw localObject2;
    }
    finally
    {
      this.b.endTransaction();
    }
  }

<com.bitdefender.security.antimalware.l: void a(java.lang.String,java.lang.String,int)>
  public final void a(String paramString1, String paramString2, int paramInt)
  {
    // Byte code:
    //   0: aload_0
    //   1: getfield 27	com/bitdefender/security/antimalware/l:e	Ljava/lang/Object;
    //   4: astore 4
    //   6: aload 4
    //   8: monitorenter
    //   9: aconst_null
    //   10: astore 5
    //   12: new 180	android/content/ContentValues
    //   15: dup
    //   16: invokespecial 181	android/content/ContentValues:<init>	()V
    //   19: astore 6
    //   21: aload_1
    //   22: ldc 183
    //   24: invokevirtual 189	java/lang/String:startsWith	(Ljava/lang/String;)Z
    //   27: ifeq +253 -> 280
    //   30: aload_1
    //   31: bipush 8
    //   33: invokevirtual 192	java/lang/String:substring	(I)Ljava/lang/String;
    //   36: astore 8
    //   38: aload 6
    //   40: ldc 194
    //   42: aload 8
    //   44: invokevirtual 197	android/content/ContentValues:put	(Ljava/lang/String;Ljava/lang/String;)V
    //   47: aload 6
    //   49: ldc 199
    //   51: iconst_0
    //   52: invokestatic 205	java/lang/Integer:valueOf	(I)Ljava/lang/Integer;
    //   55: invokevirtual 208	android/content/ContentValues:put	(Ljava/lang/String;Ljava/lang/Integer;)V
    //   58: aload 6
    //   60: ldc 210
    //   62: iload_3
    //   63: invokestatic 205	java/lang/Integer:valueOf	(I)Ljava/lang/Integer;
    //   66: invokevirtual 208	android/content/ContentValues:put	(Ljava/lang/String;Ljava/lang/Integer;)V
    //   69: aload 6
    //   71: ldc 212
    //   73: aload_2
    //   74: invokevirtual 197	android/content/ContentValues:put	(Ljava/lang/String;Ljava/lang/String;)V
    //   77: new 123	java/lang/StringBuilder
    //   80: dup
    //   81: ldc 214
    //   83: invokespecial 127	java/lang/StringBuilder:<init>	(Ljava/lang/String;)V
    //   86: iload_3
    //   87: invokevirtual 217	java/lang/StringBuilder:append	(I)Ljava/lang/StringBuilder;
    //   90: ldc 219
    //   92: invokevirtual 131	java/lang/StringBuilder:append	(Ljava/lang/String;)Ljava/lang/StringBuilder;
    //   95: aload 8
    //   97: invokevirtual 131	java/lang/StringBuilder:append	(Ljava/lang/String;)Ljava/lang/StringBuilder;
    //   100: ldc 221
    //   102: invokevirtual 131	java/lang/StringBuilder:append	(Ljava/lang/String;)Ljava/lang/StringBuilder;
    //   105: aload_1
    //   106: invokevirtual 131	java/lang/StringBuilder:append	(Ljava/lang/String;)Ljava/lang/StringBuilder;
    //   109: ldc 223
    //   111: invokevirtual 131	java/lang/StringBuilder:append	(Ljava/lang/String;)Ljava/lang/StringBuilder;
    //   114: aload_2
    //   115: invokevirtual 131	java/lang/StringBuilder:append	(Ljava/lang/String;)Ljava/lang/StringBuilder;
    //   118: ldc 225
    //   120: invokevirtual 131	java/lang/StringBuilder:append	(Ljava/lang/String;)Ljava/lang/StringBuilder;
    //   123: invokevirtual 137	java/lang/StringBuilder:toString	()Ljava/lang/String;
    //   126: astore 9
    //   128: aload_0
    //   129: invokevirtual 111	com/bitdefender/security/antimalware/l:a	()Lcom/bitdefender/security/u;
    //   132: pop
    //   133: aload_0
    //   134: getfield 114	com/bitdefender/security/antimalware/l:b	Landroid/database/sqlite/SQLiteDatabase;
    //   137: invokevirtual 119	android/database/sqlite/SQLiteDatabase:beginTransaction	()V
    //   140: aload_0
    //   141: ldc 121
    //   143: aload 9
    //   145: invokevirtual 143	com/bitdefender/security/antimalware/l:a	(Ljava/lang/String;Ljava/lang/String;)Landroid/database/Cursor;
    //   148: astore 5
    //   150: aload 5
    //   152: ifnull +106 -> 258
    //   155: aload 5
    //   157: invokeinterface 149 1 0
    //   162: ifle +49 -> 211
    //   165: aload_0
    //   166: getfield 25	com/bitdefender/security/antimalware/l:c	Lcom/bitdefender/security/bg;
    //   169: iconst_0
    //   170: invokevirtual 152	com/bitdefender/security/bg:b	(Z)V
    //   173: aload_0
    //   174: getfield 114	com/bitdefender/security/antimalware/l:b	Landroid/database/sqlite/SQLiteDatabase;
    //   177: invokevirtual 155	android/database/sqlite/SQLiteDatabase:setTransactionSuccessful	()V
    //   180: aload_0
    //   181: getfield 114	com/bitdefender/security/antimalware/l:b	Landroid/database/sqlite/SQLiteDatabase;
    //   184: invokevirtual 158	android/database/sqlite/SQLiteDatabase:endTransaction	()V
    //   187: aload 5
    //   189: ifnull +10 -> 199
    //   192: aload 5
    //   194: invokeinterface 161 1 0
    //   199: aload_0
    //   200: invokevirtual 162	com/bitdefender/security/antimalware/l:b	()V
    //   203: aload 4
    //   205: monitorexit
    //   206: aload_0
    //   207: invokespecial 164	com/bitdefender/security/antimalware/l:f	()V
    //   210: return
    //   211: aload_0
    //   212: ldc 121
    //   214: aload 6
    //   216: invokevirtual 228	com/bitdefender/security/antimalware/l:a	(Ljava/lang/String;Landroid/content/ContentValues;)V
    //   219: aload_0
    //   220: getfield 25	com/bitdefender/security/antimalware/l:c	Lcom/bitdefender/security/bg;
    //   223: iconst_0
    //   224: invokevirtual 152	com/bitdefender/security/bg:b	(Z)V
    //   227: goto -54 -> 173
    //   230: astore 12
    //   232: aload 12
    //   234: invokevirtual 165	android/database/SQLException:toString	()Ljava/lang/String;
    //   237: invokestatic 169	com/bd/android/shared/c:a	(Ljava/lang/String;)V
    //   240: aload_0
    //   241: getfield 114	com/bitdefender/security/antimalware/l:b	Landroid/database/sqlite/SQLiteDatabase;
    //   244: invokevirtual 158	android/database/sqlite/SQLiteDatabase:endTransaction	()V
    //   247: goto -60 -> 187
    //   250: astore 7
    //   252: aload 4
    //   254: monitorexit
    //   255: aload 7
    //   257: athrow
    //   258: ldc 171
    //   260: ldc 230
    //   262: invokestatic 177	com/bd/android/shared/h:a	(Ljava/lang/String;Ljava/lang/String;)V
    //   265: goto -92 -> 173
    //   268: astore 11
    //   270: aload_0
    //   271: getfield 114	com/bitdefender/security/antimalware/l:b	Landroid/database/sqlite/SQLiteDatabase;
    //   274: invokevirtual 158	android/database/sqlite/SQLiteDatabase:endTransaction	()V
    //   277: aload 11
    //   279: athrow
    //   280: aload_1
    //   281: astore 8
    //   283: goto -245 -> 38
    //
    // Exception table:
    //   from	to	target	type
    //   140	150	230	android/database/SQLException
    //   155	173	230	android/database/SQLException
    //   173	180	230	android/database/SQLException
    //   211	227	230	android/database/SQLException
    //   258	265	230	android/database/SQLException
    //   12	38	250	finally
    //   38	140	250	finally
    //   180	187	250	finally
    //   192	199	250	finally
    //   199	206	250	finally
    //   240	247	250	finally
    //   270	280	250	finally
    //   140	150	268	finally
    //   155	173	268	finally
    //   173	180	268	finally
    //   211	227	268	finally
    //   232	240	268	finally
    //   258	265	268	finally
  }

<com.bitdefender.security.antimalware.l: void a(java.util.ArrayList)>

  public final void a(ArrayList paramArrayList)
  {
    Object localObject1 = this.e;
    Cursor localCursor = null;
    while (true)
    {
      try
      {
        ContentValues localContentValues = new ContentValues();
        a();
        this.b.beginTransaction();
        try
        {
          Iterator localIterator = paramArrayList.iterator();
          if (!localIterator.hasNext())
            break label414;
          localn = (n)localIterator.next();
          localContentValues.clear();
          str1 = localn.e;
          if (str1.startsWith("Android."))
            str1 = str1.substring(8);
          localContentValues.put("THREATNAME", str1);
          localContentValues.put("ISFILE", Integer.valueOf(localn.a));
          localContentValues.put("STATUSCODE", Integer.valueOf(localn.b));
          if (localn.a == 0)
          {
            localContentValues.put("PACKAGENAME", localn.d);
            str2 = "STATUSCODE = " + localn.b + " AND THREATNAME = '" + str1 + "' AND ISFILE = " + localn.a + " AND PACKAGENAME = '" + localn.d + "'";
            localCursor = a("MALWARELIST", str2);
            if (localCursor == null)
              break label404;
            if (localCursor.getCount() <= 0)
              continue;
            this.c.b(false);
            localCursor.close();
            continue;
          }
        }
        catch (SQLException localSQLException)
        {
          n localn;
          String str1;
          c.a(localSQLException.toString());
          this.b.endTransaction();
          if (localCursor != null)
            localCursor.close();
          b();
          f();
          return;
          localContentValues.put("FILEPATH", localn.c);
          String str2 = "STATUSCODE = " + localn.b + " AND THREATNAME = '" + str1 + "' AND ISFILE = " + localn.a + " AND FILEPATH = '" + localn.c + "'";
          continue;
          a("MALWARELIST", localContentValues);
          this.c.b(false);
          continue;
        }
        finally
        {
          this.b.endTransaction();
        }
      }
      finally
      {
      }
      label404: h.a("MalwareListSQL", "LOG_GEO - ERROR executeQuery in insertMalware - MalwareListSQL");
      continue;
      label414: this.b.setTransactionSuccessful();
      this.b.endTransaction();
    }
  }

<com.bitdefender.websecurity.i: boolean b(java.lang.String,java.lang.String)>

  protected final boolean b(String paramString1, String paramString2)
  {
    // Byte code:
    //   0: aload_0
    //   1: getfield 32	com/bitdefender/websecurity/i:e	Ljava/lang/Object;
    //   4: astore_3
    //   5: aload_3
    //   6: monitorenter
    //   7: aconst_null
    //   8: astore 4
    //   10: aload_0
    //   11: invokevirtual 62	com/bitdefender/websecurity/i:a	()Lcom/bitdefender/websecurity/a;
    //   14: pop
    //   15: new 64	java/lang/StringBuilder
    //   18: dup
    //   19: ldc 66
    //   21: invokespecial 69	java/lang/StringBuilder:<init>	(Ljava/lang/String;)V
    //   24: aload_1
    //   25: invokevirtual 73	java/lang/StringBuilder:append	(Ljava/lang/String;)Ljava/lang/StringBuilder;
    //   28: ldc 137
    //   30: invokevirtual 73	java/lang/StringBuilder:append	(Ljava/lang/String;)Ljava/lang/StringBuilder;
    //   33: aload_2
    //   34: invokevirtual 73	java/lang/StringBuilder:append	(Ljava/lang/String;)Ljava/lang/StringBuilder;
    //   37: ldc 77
    //   39: invokevirtual 73	java/lang/StringBuilder:append	(Ljava/lang/String;)Ljava/lang/StringBuilder;
    //   42: invokevirtual 81	java/lang/StringBuilder:toString	()Ljava/lang/String;
    //   45: astore 8
    //   47: aload_0
    //   48: ldc 83
    //   50: aload_0
    //   51: getfield 30	com/bitdefender/websecurity/i:c	[Ljava/lang/String;
    //   54: aload 8
    //   56: invokevirtual 86	com/bitdefender/websecurity/i:a	(Ljava/lang/String;[Ljava/lang/String;Ljava/lang/String;)Landroid/database/Cursor;
    //   59: astore 4
    //   61: aload 4
    //   63: ifnull +208 -> 271
    //   66: aload 4
    //   68: invokeinterface 92 1 0
    //   73: ifle +198 -> 271
    //   76: aload 4
    //   78: invokeinterface 141 1 0
    //   83: ifeq +173 -> 256
    //   86: invokestatic 147	java/lang/System:currentTimeMillis	()J
    //   89: aload 4
    //   91: aload 4
    //   93: ldc 28
    //   95: invokeinterface 151 2 0
    //   100: invokeinterface 155 2 0
    //   105: lsub
    //   106: ldc2_w 156
    //   109: lcmp
    //   110: ifle +146 -> 256
    //   113: aload_0
    //   114: getfield 99	com/bitdefender/websecurity/i:b	Landroid/database/sqlite/SQLiteDatabase;
    //   117: invokevirtual 119	android/database/sqlite/SQLiteDatabase:beginTransaction	()V
    //   120: aload_0
    //   121: ldc 83
    //   123: aload 8
    //   125: invokevirtual 158	com/bitdefender/websecurity/i:a	(Ljava/lang/String;Ljava/lang/String;)V
    //   128: aload_0
    //   129: getfield 99	com/bitdefender/websecurity/i:b	Landroid/database/sqlite/SQLiteDatabase;
    //   132: invokevirtual 125	android/database/sqlite/SQLiteDatabase:setTransactionSuccessful	()V
    //   135: aload_0
    //   136: getfield 99	com/bitdefender/websecurity/i:b	Landroid/database/sqlite/SQLiteDatabase;
    //   139: invokevirtual 104	android/database/sqlite/SQLiteDatabase:endTransaction	()V
    //   142: aload 4
    //   144: invokeinterface 95 1 0
    //   149: aload_0
    //   150: invokevirtual 106	com/bitdefender/websecurity/i:b	()V
    //   153: aload_3
    //   154: monitorexit
    //   155: iconst_0
    //   156: ireturn
    //   157: astore 10
    //   159: new 64	java/lang/StringBuilder
    //   162: dup
    //   163: ldc 160
    //   165: invokespecial 69	java/lang/StringBuilder:<init>	(Ljava/lang/String;)V
    //   168: aload 10
    //   170: invokevirtual 128	android/database/SQLException:toString	()Ljava/lang/String;
    //   173: invokevirtual 73	java/lang/StringBuilder:append	(Ljava/lang/String;)Ljava/lang/StringBuilder;
    //   176: invokevirtual 81	java/lang/StringBuilder:toString	()Ljava/lang/String;
    //   179: invokestatic 132	com/bd/android/shared/c:a	(Ljava/lang/String;)V
    //   182: aload_0
    //   183: getfield 99	com/bitdefender/websecurity/i:b	Landroid/database/sqlite/SQLiteDatabase;
    //   186: invokevirtual 104	android/database/sqlite/SQLiteDatabase:endTransaction	()V
    //   189: goto -47 -> 142
    //   192: astore 6
    //   194: new 64	java/lang/StringBuilder
    //   197: dup
    //   198: ldc 160
    //   200: invokespecial 69	java/lang/StringBuilder:<init>	(Ljava/lang/String;)V
    //   203: aload 6
    //   205: invokevirtual 161	java/lang/Exception:toString	()Ljava/lang/String;
    //   208: invokevirtual 73	java/lang/StringBuilder:append	(Ljava/lang/String;)Ljava/lang/StringBuilder;
    //   211: invokevirtual 81	java/lang/StringBuilder:toString	()Ljava/lang/String;
    //   214: invokestatic 132	com/bd/android/shared/c:a	(Ljava/lang/String;)V
    //   217: aload 4
    //   219: ifnull +10 -> 229
    //   222: aload 4
    //   224: invokeinterface 95 1 0
    //   229: aload_0
    //   230: invokevirtual 106	com/bitdefender/websecurity/i:b	()V
    //   233: aload_3
    //   234: monitorexit
    //   235: iconst_0
    //   236: ireturn
    //   237: astore 5
    //   239: aload_3
    //   240: monitorexit
    //   241: aload 5
    //   243: athrow
    //   244: astore 9
    //   246: aload_0
    //   247: getfield 99	com/bitdefender/websecurity/i:b	Landroid/database/sqlite/SQLiteDatabase;
    //   250: invokevirtual 104	android/database/sqlite/SQLiteDatabase:endTransaction	()V
    //   253: aload 9
    //   255: athrow
    //   256: aload 4
    //   258: invokeinterface 95 1 0
    //   263: aload_0
    //   264: invokevirtual 106	com/bitdefender/websecurity/i:b	()V
    //   267: aload_3
    //   268: monitorexit
    //   269: iconst_1
    //   270: ireturn
    //   271: aload 4
    //   273: ifnull +10 -> 283
    //   276: aload 4
    //   278: invokeinterface 95 1 0
    //   283: aload_0
    //   284: invokevirtual 106	com/bitdefender/websecurity/i:b	()V
    //   287: aload_3
    //   288: monitorexit
    //   289: iconst_0
    //   290: ireturn
    //
    // Exception table:
    //   from	to	target	type
    //   120	135	157	android/database/SQLException
    //   10	61	192	java/lang/Exception
    //   66	120	192	java/lang/Exception
    //   135	142	192	java/lang/Exception
    //   142	153	192	java/lang/Exception
    //   182	189	192	java/lang/Exception
    //   246	256	192	java/lang/Exception
    //   256	267	192	java/lang/Exception
    //   276	283	192	java/lang/Exception
    //   283	287	192	java/lang/Exception
    //   10	61	237	finally
    //   66	120	237	finally
    //   135	142	237	finally
    //   142	153	237	finally
    //   153	155	237	finally
    //   182	189	237	finally
    //   194	217	237	finally
    //   222	229	237	finally
    //   229	235	237	finally
    //   246	256	237	finally
    //   256	267	237	finally
    //   267	269	237	finally
    //   276	283	237	finally
    //   283	287	237	finally
    //   287	289	237	finally
    //   120	135	244	finally
    //   159	182	244	finally
  }

<com.bitdefender.security.antimalware.l: void b(java.lang.String)>
  public final void b(String paramString)
  {
    Cursor localCursor = null;
    synchronized (this.e)
    {
      a();
      this.b.beginTransaction();
    }
    try
    {
      b("MALWARELIST", "FILEPATH = '" + paramString + "' AND ISFILE = 1");
      localCursor = a("MALWARELIST", null);
      if (localCursor != null)
      {
        if (localCursor.getCount() == 0)
          this.c.b(true);
        while (true)
        {
          this.b.setTransactionSuccessful();
          this.b.endTransaction();
          if (localCursor != null)
            localCursor.close();
          b();
          f();
          return;
          this.c.b(false);
        }
      }
    }
    catch (SQLException localSQLException)
    {
      while (true)
      {
        c.a(localSQLException.toString());
        this.b.endTransaction();
        continue;
        localObject2 = finally;
        throw localObject2;
        h.a("MalwareListSQL", "LOG_GEO - ERROR executeQuery in deleteMalwareFile - MalwareListSQL");
      }
    }
    finally
    {
      this.b.endTransaction();
    }
  }

