Need to verify:true begin method@[<com.anttek.mmslib.providers.telephony.MmsSmsDatabaseHelper: void onUpgrade(android.database.sqlite.SQLiteDatabase,int,int)>] lock method@[]


  public void onUpgrade(SQLiteDatabase paramSQLiteDatabase, int paramInt1, int paramInt2)
  {
    // Byte code:
    //   0: ldc 41
    //   2: new 147	java/lang/StringBuilder
    //   5: dup
    //   6: invokespecial 149	java/lang/StringBuilder:<init>	()V
    //   9: ldc_w 554
    //   12: invokevirtual 155	java/lang/StringBuilder:append	(Ljava/lang/String;)Ljava/lang/StringBuilder;
    //   15: iload_2
    //   16: invokevirtual 195	java/lang/StringBuilder:append	(I)Ljava/lang/StringBuilder;
    //   19: ldc_w 556
    //   22: invokevirtual 155	java/lang/StringBuilder:append	(Ljava/lang/String;)Ljava/lang/StringBuilder;
    //   25: iload_3
    //   26: invokevirtual 195	java/lang/StringBuilder:append	(I)Ljava/lang/StringBuilder;
    //   29: ldc_w 558
    //   32: invokevirtual 155	java/lang/StringBuilder:append	(Ljava/lang/String;)Ljava/lang/StringBuilder;
    //   35: invokevirtual 160	java/lang/StringBuilder:toString	()Ljava/lang/String;
    //   38: invokestatic 561	android/util/Log:w	(Ljava/lang/String;Ljava/lang/String;)I
    //   41: pop
    //   42: iload_2
    //   43: tableswitch	default:+65 -> 108, 40:+85->128, 41:+108->151, 42:+131->174, 43:+154->197, 44:+177->220, 45:+200->243, 46:+223->266, 47:+246->289, 48:+269->312, 49:+292->335, 50:+315->358, 51:+338->381, 52:+344->387
    //   109: dload_3
    //   110: ldc_w 563
    //   113: invokestatic 166	android/util/Log:e	(Ljava/lang/String;Ljava/lang/String;)I
    //   116: pop
    //   117: aload_0
    //   118: aload_1
    //   119: invokespecial 565	com/anttek/mmslib/providers/telephony/MmsSmsDatabaseHelper:dropAll	(Landroid/database/sqlite/SQLiteDatabase;)V
    //   122: aload_0
    //   123: aload_1
    //   124: invokevirtual 567	com/anttek/mmslib/providers/telephony/MmsSmsDatabaseHelper:onCreate	(Landroid/database/sqlite/SQLiteDatabase;)V
    //   127: return
    //   128: iload_3
    //   129: bipush 40
    //   131: if_icmple -4 -> 127
    //   134: aload_1
    //   135: invokevirtual 570	android/database/sqlite/SQLiteDatabase:beginTransaction	()V
    //   138: aload_0
    //   139: aload_1
    //   140: invokespecial 572	com/anttek/mmslib/providers/telephony/MmsSmsDatabaseHelper:upgradeDatabaseToVersion41	(Landroid/database/sqlite/SQLiteDatabase;)V
    //   143: aload_1
    //   144: invokevirtual 575	android/database/sqlite/SQLiteDatabase:setTransactionSuccessful	()V
    //   147: aload_1
    //   148: invokevirtual 578	android/database/sqlite/SQLiteDatabase:endTransaction	()V
    //   151: iload_3
    //   152: bipush 41
    //   154: if_icmple -27 -> 127
    //   157: aload_1
    //   158: invokevirtual 570	android/database/sqlite/SQLiteDatabase:beginTransaction	()V
    //   161: aload_0
    //   162: aload_1
    //   163: invokespecial 580	com/anttek/mmslib/providers/telephony/MmsSmsDatabaseHelper:upgradeDatabaseToVersion42	(Landroid/database/sqlite/SQLiteDatabase;)V
    //   166: aload_1
    //   167: invokevirtual 575	android/database/sqlite/SQLiteDatabase:setTransactionSuccessful	()V
    //   170: aload_1
    //   171: invokevirtual 578	android/database/sqlite/SQLiteDatabase:endTransaction	()V
    //   174: iload_3
    //   175: bipush 42
    //   177: if_icmple -50 -> 127
    //   180: aload_1
    //   181: invokevirtual 570	android/database/sqlite/SQLiteDatabase:beginTransaction	()V
    //   184: aload_0
    //   185: aload_1
    //   186: invokespecial 582	com/anttek/mmslib/providers/telephony/MmsSmsDatabaseHelper:upgradeDatabaseToVersion43	(Landroid/database/sqlite/SQLiteDatabase;)V
    //   189: aload_1
    //   190: invokevirtual 575	android/database/sqlite/SQLiteDatabase:setTransactionSuccessful	()V
    //   193: aload_1
    //   194: invokevirtual 578	android/database/sqlite/SQLiteDatabase:endTransaction	()V
    //   197: iload_3
    //   198: bipush 43
    //   200: if_icmple -73 -> 127
    //   203: aload_1
    //   204: invokevirtual 570	android/database/sqlite/SQLiteDatabase:beginTransaction	()V
    //   207: aload_0
    //   208: aload_1
    //   209: invokespecial 584	com/anttek/mmslib/providers/telephony/MmsSmsDatabaseHelper:upgradeDatabaseToVersion44	(Landroid/database/sqlite/SQLiteDatabase;)V
    //   212: aload_1
    //   213: invokevirtual 575	android/database/sqlite/SQLiteDatabase:setTransactionSuccessful	()V
    //   216: aload_1
    //   217: invokevirtual 578	android/database/sqlite/SQLiteDatabase:endTransaction	()V
    //   220: iload_3
    //   221: bipush 44
    //   223: if_icmple -96 -> 127
    //   226: aload_1
    //   227: invokevirtual 570	android/database/sqlite/SQLiteDatabase:beginTransaction	()V
    //   230: aload_0
    //   231: aload_1
    //   232: invokespecial 586	com/anttek/mmslib/providers/telephony/MmsSmsDatabaseHelper:upgradeDatabaseToVersion45	(Landroid/database/sqlite/SQLiteDatabase;)V
    //   235: aload_1
    //   236: invokevirtual 575	android/database/sqlite/SQLiteDatabase:setTransactionSuccessful	()V
    //   239: aload_1
    //   240: invokevirtual 578	android/database/sqlite/SQLiteDatabase:endTransaction	()V
    //   243: iload_3
    //   244: bipush 45
    //   246: if_icmple -119 -> 127
    //   249: aload_1
    //   250: invokevirtual 570	android/database/sqlite/SQLiteDatabase:beginTransaction	()V
    //   253: aload_0
    //   254: aload_1
    //   255: invokespecial 588	com/anttek/mmslib/providers/telephony/MmsSmsDatabaseHelper:upgradeDatabaseToVersion46	(Landroid/database/sqlite/SQLiteDatabase;)V
    //   258: aload_1
    //   259: invokevirtual 575	android/database/sqlite/SQLiteDatabase:setTransactionSuccessful	()V
    //   262: aload_1
    //   263: invokevirtual 578	android/database/sqlite/SQLiteDatabase:endTransaction	()V
    //   266: iload_3
    //   267: bipush 46
    //   269: if_icmple -142 -> 127
    //   272: aload_1
    //   273: invokevirtual 570	android/database/sqlite/SQLiteDatabase:beginTransaction	()V
    //   276: aload_0
    //   277: aload_1
    //   278: invokespecial 590	com/anttek/mmslib/providers/telephony/MmsSmsDatabaseHelper:upgradeDatabaseToVersion47	(Landroid/database/sqlite/SQLiteDatabase;)V
    //   281: aload_1
    //   282: invokevirtual 575	android/database/sqlite/SQLiteDatabase:setTransactionSuccessful	()V
    //   285: aload_1
    //   286: invokevirtual 578	android/database/sqlite/SQLiteDatabase:endTransaction	()V
    //   289: iload_3
    //   290: bipush 47
    //   292: if_icmple -165 -> 127
    //   295: aload_1
    //   296: invokevirtual 570	android/database/sqlite/SQLiteDatabase:beginTransaction	()V
    //   299: aload_0
    //   300: aload_1
    //   301: invokespecial 592	com/anttek/mmslib/providers/telephony/MmsSmsDatabaseHelper:upgradeDatabaseToVersion48	(Landroid/database/sqlite/SQLiteDatabase;)V
    //   304: aload_1
    //   305: invokevirtual 575	android/database/sqlite/SQLiteDatabase:setTransactionSuccessful	()V
    //   308: aload_1
    //   309: invokevirtual 578	android/database/sqlite/SQLiteDatabase:endTransaction	()V
    //   312: iload_3
    //   313: bipush 48
    //   315: if_icmple -188 -> 127
    //   318: aload_1
    //   319: invokevirtual 570	android/database/sqlite/SQLiteDatabase:beginTransaction	()V
    //   322: aload_0
    //   323: aload_1
    //   324: invokespecial 546	com/anttek/mmslib/providers/telephony/MmsSmsDatabaseHelper:createWordsTables	(Landroid/database/sqlite/SQLiteDatabase;)V
    //   327: aload_1
    //   328: invokevirtual 575	android/database/sqlite/SQLiteDatabase:setTransactionSuccessful	()V
    //   331: aload_1
    //   332: invokevirtual 578	android/database/sqlite/SQLiteDatabase:endTransaction	()V
    //   335: iload_3
    //   336: bipush 49
    //   338: if_icmple -211 -> 127
    //   341: aload_1
    //   342: invokevirtual 570	android/database/sqlite/SQLiteDatabase:beginTransaction	()V
    //   345: aload_0
    //   346: aload_1
    //   347: invokespecial 114	com/anttek/mmslib/providers/telephony/MmsSmsDatabaseHelper:createThreadIdIndex	(Landroid/database/sqlite/SQLiteDatabase;)V
    //   350: aload_1
    //   351: invokevirtual 575	android/database/sqlite/SQLiteDatabase:setTransactionSuccessful	()V
    //   354: aload_1
    //   355: invokevirtual 578	android/database/sqlite/SQLiteDatabase:endTransaction	()V
    //   358: iload_3
    //   359: bipush 50
    //   361: if_icmple -234 -> 127
    //   364: aload_1
    //   365: invokevirtual 570	android/database/sqlite/SQLiteDatabase:beginTransaction	()V
    //   368: aload_0
    //   369: aload_1
    //   370: invokespecial 594	com/anttek/mmslib/providers/telephony/MmsSmsDatabaseHelper:upgradeDatabaseToVersion51	(Landroid/database/sqlite/SQLiteDatabase;)V
    //   373: aload_1
    //   374: invokevirtual 575	android/database/sqlite/SQLiteDatabase:setTransactionSuccessful	()V
    //   377: aload_1
    //   378: invokevirtual 578	android/database/sqlite/SQLiteDatabase:endTransaction	()V
    //   381: iload_3
    //   382: bipush 51
    //   384: if_icmple -257 -> 127
    //   387: iload_3
    //   388: bipush 52
    //   390: if_icmple -263 -> 127
    //   393: aload_1
    //   394: invokevirtual 570	android/database/sqlite/SQLiteDatabase:beginTransaction	()V
    //   397: aload_0
    //   398: aload_1
    //   399: invokespecial 596	com/anttek/mmslib/providers/telephony/MmsSmsDatabaseHelper:upgradeDatabaseToVersion53	(Landroid/database/sqlite/SQLiteDatabase;)V
    //   402: aload_1
    //   403: invokevirtual 575	android/database/sqlite/SQLiteDatabase:setTransactionSuccessful	()V
    //   406: aload_1
    //   407: invokevirtual 578	android/database/sqlite/SQLiteDatabase:endTransaction	()V
    //   410: return
    //   411: astore 40
    //   413: ldc 41
    //   415: aload 40
    //   417: invokevirtual 599	java/lang/Throwable:getMessage	()Ljava/lang/String;
    //   420: aload 40
    //   422: invokestatic 500	android/util/Log:e	(Ljava/lang/String;Ljava/lang/String;Ljava/lang/Throwable;)I
    //   425: pop
    //   426: aload_1
    //   427: invokevirtual 578	android/database/sqlite/SQLiteDatabase:endTransaction	()V
    //   430: goto -322 -> 108
    //   433: astore 39
    //   435: aload_1
    //   436: invokevirtual 578	android/database/sqlite/SQLiteDatabase:endTransaction	()V
    //   439: aload 39
    //   441: athrow
    //   442: astore 37
    //   444: ldc 41
    //   446: aload 37
    //   448: invokevirtual 599	java/lang/Throwable:getMessage	()Ljava/lang/String;
    //   451: aload 37
    //   453: invokestatic 500	android/util/Log:e	(Ljava/lang/String;Ljava/lang/String;Ljava/lang/Throwable;)I
    //   456: pop
    //   457: aload_1
    //   458: invokevirtual 578	android/database/sqlite/SQLiteDatabase:endTransaction	()V
    //   461: goto -353 -> 108
    //   464: astore 36
    //   466: aload_1
    //   467: invokevirtual 578	android/database/sqlite/SQLiteDatabase:endTransaction	()V
    //   470: aload 36
    //   472: athrow
    //   473: astore 34
    //   475: ldc 41
    //   477: aload 34
    //   479: invokevirtual 599	java/lang/Throwable:getMessage	()Ljava/lang/String;
    //   482: aload 34
    //   484: invokestatic 500	android/util/Log:e	(Ljava/lang/String;Ljava/lang/String;Ljava/lang/Throwable;)I
    //   487: pop
    //   488: aload_1
    //   489: invokevirtual 578	android/database/sqlite/SQLiteDatabase:endTransaction	()V
    //   492: goto -384 -> 108
    //   495: astore 33
    //   497: aload_1
    //   498: invokevirtual 578	android/database/sqlite/SQLiteDatabase:endTransaction	()V
    //   501: aload 33
    //   503: athrow
    //   504: astore 31
    //   506: ldc 41
    //   508: aload 31
    //   510: invokevirtual 599	java/lang/Throwable:getMessage	()Ljava/lang/String;
    //   513: aload 31
    //   515: invokestatic 500	android/util/Log:e	(Ljava/lang/String;Ljava/lang/String;Ljava/lang/Throwable;)I
    //   518: pop
    //   519: aload_1
    //   520: invokevirtual 578	android/database/sqlite/SQLiteDatabase:endTransaction	()V
    //   523: goto -415 -> 108
    //   526: astore 30
    //   528: aload_1
    //   529: invokevirtual 578	android/database/sqlite/SQLiteDatabase:endTransaction	()V
    //   532: aload 30
    //   534: athrow
    //   535: astore 28
    //   537: ldc 41
    //   539: aload 28
    //   541: invokevirtual 599	java/lang/Throwable:getMessage	()Ljava/lang/String;
    //   544: aload 28
    //   546: invokestatic 500	android/util/Log:e	(Ljava/lang/String;Ljava/lang/String;Ljava/lang/Throwable;)I
    //   549: pop
    //   550: aload_1
    //   551: invokevirtual 578	android/database/sqlite/SQLiteDatabase:endTransaction	()V
    //   554: goto -446 -> 108
    //   557: astore 27
    //   559: aload_1
    //   560: invokevirtual 578	android/database/sqlite/SQLiteDatabase:endTransaction	()V
    //   563: aload 27
    //   565: athrow
    //   566: astore 25
    //   568: ldc 41
    //   570: aload 25
    //   572: invokevirtual 599	java/lang/Throwable:getMessage	()Ljava/lang/String;
    //   575: aload 25
    //   577: invokestatic 500	android/util/Log:e	(Ljava/lang/String;Ljava/lang/String;Ljava/lang/Throwable;)I
    //   580: pop
    //   581: aload_1
    //   582: invokevirtual 578	android/database/sqlite/SQLiteDatabase:endTransaction	()V
    //   585: goto -477 -> 108
    //   588: astore 24
    //   590: aload_1
    //   591: invokevirtual 578	android/database/sqlite/SQLiteDatabase:endTransaction	()V
    //   594: aload 24
    //   596: athrow
    //   597: astore 22
    //   599: ldc 41
    //   601: aload 22
    //   603: invokevirtual 599	java/lang/Throwable:getMessage	()Ljava/lang/String;
    //   606: aload 22
    //   608: invokestatic 500	android/util/Log:e	(Ljava/lang/String;Ljava/lang/String;Ljava/lang/Throwable;)I
    //   611: pop
    //   612: aload_1
    //   613: invokevirtual 578	android/database/sqlite/SQLiteDatabase:endTransaction	()V
    //   616: goto -508 -> 108
    //   619: astore 21
    //   621: aload_1
    //   622: invokevirtual 578	android/database/sqlite/SQLiteDatabase:endTransaction	()V
    //   625: aload 21
    //   627: athrow
    //   628: astore 19
    //   630: ldc 41
    //   632: aload 19
    //   634: invokevirtual 599	java/lang/Throwable:getMessage	()Ljava/lang/String;
    //   637: aload 19
    //   639: invokestatic 500	android/util/Log:e	(Ljava/lang/String;Ljava/lang/String;Ljava/lang/Throwable;)I
    //   642: pop
    //   643: aload_1
    //   644: invokevirtual 578	android/database/sqlite/SQLiteDatabase:endTransaction	()V
    //   647: goto -539 -> 108
    //   650: astore 18
    //   652: aload_1
    //   653: invokevirtual 578	android/database/sqlite/SQLiteDatabase:endTransaction	()V
    //   656: aload 18
    //   658: athrow
    //   659: astore 16
    //   661: ldc 41
    //   663: aload 16
    //   665: invokevirtual 599	java/lang/Throwable:getMessage	()Ljava/lang/String;
    //   668: aload 16
    //   670: invokestatic 500	android/util/Log:e	(Ljava/lang/String;Ljava/lang/String;Ljava/lang/Throwable;)I
    //   673: pop
    //   674: aload_1
    //   675: invokevirtual 578	android/database/sqlite/SQLiteDatabase:endTransaction	()V
    //   678: goto -570 -> 108
    //   681: astore 15
    //   683: aload_1
    //   684: invokevirtual 578	android/database/sqlite/SQLiteDatabase:endTransaction	()V
    //   687: aload 15
    //   689: athrow
    //   690: astore 13
    //   692: ldc 41
    //   694: aload 13
    //   696: invokevirtual 599	java/lang/Throwable:getMessage	()Ljava/lang/String;
    //   699: aload 13
    //   701: invokestatic 500	android/util/Log:e	(Ljava/lang/String;Ljava/lang/String;Ljava/lang/Throwable;)I
    //   704: pop
    //   705: aload_1
    //   706: invokevirtual 578	android/database/sqlite/SQLiteDatabase:endTransaction	()V
    //   709: goto -601 -> 108
    //   712: astore 12
    //   714: aload_1
    //   715: invokevirtual 578	android/database/sqlite/SQLiteDatabase:endTransaction	()V
    //   718: aload 12
    //   720: athrow
    //   721: astore 10
    //   723: ldc 41
    //   725: aload 10
    //   727: invokevirtual 599	java/lang/Throwable:getMessage	()Ljava/lang/String;
    //   730: aload 10
    //   732: invokestatic 500	android/util/Log:e	(Ljava/lang/String;Ljava/lang/String;Ljava/lang/Throwable;)I
    //   735: pop
    //   736: aload_1
    //   737: invokevirtual 578	android/database/sqlite/SQLiteDatabase:endTransaction	()V
    //   740: goto -632 -> 108
    //   743: astore 9
    //   745: aload_1
    //   746: invokevirtual 578	android/database/sqlite/SQLiteDatabase:endTransaction	()V
    //   749: aload 9
    //   751: athrow
    //   752: astore 6
    //   754: ldc 41
    //   756: aload 6
    //   758: invokevirtual 599	java/lang/Throwable:getMessage	()Ljava/lang/String;
    //   761: aload 6
    //   763: invokestatic 500	android/util/Log:e	(Ljava/lang/String;Ljava/lang/String;Ljava/lang/Throwable;)I
    //   766: pop
    //   767: aload_1
    //   768: invokevirtual 578	android/database/sqlite/SQLiteDatabase:endTransaction	()V
    //   771: goto -663 -> 108
    //   774: astore 5
    //   776: aload_1
    //   777: invokevirtual 578	android/database/sqlite/SQLiteDatabase:endTransaction	()V
    //   780: aload 5
    //   782: athrow
    //
    // Exception table:
    //   from	to	target	type
    //   138	147	411	java/lang/Throwable
    //   138	147	433	finally
    //   413	426	433	finally
    //   161	170	442	java/lang/Throwable
    //   161	170	464	finally
    //   444	457	464	finally
    //   184	193	473	java/lang/Throwable
    //   184	193	495	finally
    //   475	488	495	finally
    //   207	216	504	java/lang/Throwable
    //   207	216	526	finally
    //   506	519	526	finally
    //   230	239	535	java/lang/Throwable
    //   230	239	557	finally
    //   537	550	557	finally
    //   253	262	566	java/lang/Throwable
    //   253	262	588	finally
    //   568	581	588	finally
    //   276	285	597	java/lang/Throwable
    //   276	285	619	finally
    //   599	612	619	finally
    //   299	308	628	java/lang/Throwable
    //   299	308	650	finally
    //   630	643	650	finally
    //   322	331	659	java/lang/Throwable
    //   322	331	681	finally
    //   661	674	681	finally
    //   345	354	690	java/lang/Throwable
    //   345	354	712	finally
    //   692	705	712	finally
    //   368	377	721	java/lang/Throwable
    //   368	377	743	finally
    //   723	736	743	finally
    //   397	406	752	java/lang/Throwable
    //   397	406	774	finally
    //   754	767	774	finally
  }
